nais/Cluster.py
nais/Datareader.py
nais/Decomposition.py
nais/Initializers.py
nais/Mixture.py
nais/Regularizers.py
nais/Tuning.py
nais/__init__.py
nais/metrics.py
nais/utils.py
nais/Augment/__init__.py
nais/Augment/crop.py
nais/Augment/spectrogram.py
nais/Layers/__init__.py
nais/Layers/attention.py
nais/Layers/conv.py
nais/Layers/cossim.py
nais/Layers/feedforward.py
nais/Layers/patches.py
nais/Layers/pooling.py
nais/Layers/resampling.py
nais/Layers/residual.py
nais/Layers/scatter.py
nais/Layers/spectrogram.py
nais/Layers/temporal.py
nais/Layers/transformer.py
nais/Models/__init__.py
nais/Models/alexnet.py
nais/Models/autoencoder.py
nais/Models/epick.py
nais/Models/eqtransformer.py
nais/Models/patchtransphasenet.py
nais/Models/phasenet.py
nais/Models/scatnet.py
nais/Models/spectrogram.py
nais/Models/transphasenet.py
nais/Models/utime.py
nais/Models/wavenet.py
nais-1.4.dist-info/LICENSE
nais-1.4.dist-info/METADATA
nais-1.4.dist-info/WHEEL
nais-1.4.dist-info/top_level.txt
nais-1.4.dist-info/RECORD
