Metadata-Version: 2.1
Name: nais
Version: 1.4
Summary: NORSAR AI System.
Home-page: https://github.com/NorwegianSeismicArray/nais
Download-URL: https://github.com/NorwegianSeismicArray/nais/archive/refs/tags/1.0.tar.gz
Author: Erik B. Myklebust & Tord S. Stangeland
Author-email: tord@norsar.no
Classifier: Programming Language :: Python :: 3
Classifier: License :: OSI Approved :: MIT License
Classifier: Operating System :: OS Independent
Requires-Python: >=3.6
License-File: LICENSE
Requires-Dist: numpy
Requires-Dist: scipy
Requires-Dist: tensorflow
Requires-Dist: keras-tuner
Requires-Dist: scikit-learn
Requires-Dist: pandas
Requires-Dist: tqdm
Requires-Dist: pillow
